Workbook

Sheet Summary
A1: Month | B1: Statement Period | C1: Account No | D1: Beginning Balance ($) | E1: Addition ($) | F1: Subtraction ($) | G1: Trade Transaction ($) | H1: Cost and Fees ($) | I1: Ending Cash ($) | J1: Long ($) | K1: Total Market Value ($) | L1: Dividend ($) | M1: Interest ($) | N1: Realized ST Net ($) | O1: Realized LT Net ($)
A2: 2023-01 | B2: January 2023 | C2: 947159514 | E2: 34.05 | G2: -30.01 | H2: -0.02 | I2: 4.02 | J2: 32.59 | K2: 36.61
A3: 2023-02 | B3: February 2023 | C3: 947159514 | D3: 4.02 | E3: 53.72 | G3: -57.68 | H3: -0.05 | I3: 0.01 | J3: 81.09 | K3: 81.1
A4: 2023-03 | B4: March 2023 | C4: 947159514 | D4: 0.01 | I4: 0.01 | J4: 85.28 | K4: 85.29
A5: 2023-04 | B5: April 2023 | C5: 947159514 | D5: 0.01 | I5: 0.01 | J5: 82.54 | K5: 82.55
A6: 2023-05 | B6: May 2023 | C6: 947159514 | D6: 0.01 | I6: 0.01 | J6: 78.23 | K6: 78.24
A7: 2023-06 | B7: June 2023 | C7: 947159514 | D7: 0.01 | E7: 0.47 | F7: 0.06 | I7: 0.42 | J7: 81.73 | K7: 82.15 | L7: 0.47
A8: 2023-07 | B8: July 2023 | C8: 947159514 | D8: 0.42 | E8: 0.06 | I8: 0.48 | J8: 91 | K8: 91.48 | L8: 0.06
A9: 2023-08 | B9: August 2023 | C9: 947159514 | D9: 0.48 | I9: 0.48 | J9: 85.73 | K9: 86.21
A10: 2023-09 | B10: September 2023 | C10: 947159514 | D10: 0.48 | I10: 0.48 | J10: 80.44 | K10: 80.92
A11: 2023-10 | B11: October 2023 | C11: 947159514 | D11: 0.48 | I11: 0.48 | J11: 73.92 | K11: 74.4
A12: 2023-11 | B12: November 2023 | C12: 947159514 | D12: 0.48 | I12: 0.48 | J12: 78.49 | K12: 78.97
A13: 2023-12 | B13: December 2023 | C13: 947159514 | D13: 0.48 | E13: 120.56 | F13: 0.16 | G13: -119.37 | H13: -0.11 | I13: 1.4 | J13: 202.83 | K13: 204.23 | L13: 1.08
A14: 2024-01 | B14: January 2024 | C14: 947159514 | D14: 1.4 | E14: 40.1 | F14: 0.01 | G14: -33.52 | I14: 7.97 | J14: 225 | K14: 232.97 | L14: 0.1
A15: 2024-02 | B15: February 2024 | C15: 947159514 | D15: 7.97 | E15: 141.2 | G15: -141.2 | I15: 7.97 | J15: 407.56 | K15: 415.53
A16: 2024-03 | B16: March 2024 | C16: 947159514 | D16: 7.97 | E16: 309.73 | F16: 0.17 | G16: -308.11 | H16: -0.41 | I16: 9.01 | J16: 718.85 | K16: 727.86 | L16: 1.21
A17: 2024-04 | B17: April 2024 | C17: 947159514 | D17: 9.01 | E17: 3099.67 | F17: 2.52 | G17: -3081.8 | H17: -0.34 | I17: 24.02 | J17: 3767.26 | K17: 3791.28 | L17: 16.92
A18: 2024-05 | B18: May 2024 | C18: 947159514 | D18: 24.02 | E18: 4183.54 | F18: 486.15 | G18: -3677.87 | H18: -2.46 | I18: 41.08 | J18: 7463.61 | K18: 7504.69 | L18: 34.54
A19: 2024-06 | B19: June 2024 | C19: 947159514 | D19: 41.08 | E19: 2241.45 | F19: 8.65 | G19: -2230.18 | H19: -1.44 | I19: 42.26 | J19: 9674.47 | K19: 9716.73 | L19: 57.95
A20: 2024-07 | B20: July 2024 | C20: 947159514 | D20: 42.26 | E20: 11392.26 | F20: 17.96 | G20: -4012.4 | H20: -5.05 | I20: 7399.11 | J20: 13605.71 | K20: 21004.82 | L20: 120.15
A21: 2024-08 | B21: August 2024 | C21: 947159514 | D21: 7399.11 | E21: 128.74 | F21: 18.17 | G21: -6205.5 | H21: -5.28 | I21: 1298.9 | J21: 19769.4 | K21: 21068.3 | L21: 122.08
A22: 2024-09 | B22: September 2024 | C22: 947159514 | D22: 1298.9 | E22: 1719.26 | F22: 26.97 | G22: -182 | I22: 2809.19 | J22: 19945.55 | K22: 22754.74 | L22: 180.33
A23: 2024-10 | B23: October 2024 | C23: 947159514 | D23: 2809.19 | E23: 320.05 | F23: 47.91 | G23: -2474.84 | H23: -3.06 | I23: 603.43 | J23: 22294.98 | K23: 22898.41 | L23: 320.05
A24: 2024-11 | B24: November 2024 | C24: 947159514 | D24: 603.43 | E24: 3583.02 | F24: 57.1 | G24: -1713.06 | H24: -2.06 | I24: 2414.23 | J24: 24246.06 | K24: 26660.29 | L24: 381.16
A25: 2024-12 | B25: December 2024 | C25: 947159514 | D25: 2414.23 | E25: 2672.16 | F25: 272.21 | G25: -4774.95 | H25: -6.34 | I25: 32.89 | J25: 28334.96 | K25: 28367.85 | L25: 320.05 | M25: 89.42
A26: 2025-01 | B26: January 2025 | C26: 947159514 | D26: 32.89 | E26: 1975.01 | F26: 49.16 | G26: -1789.46 | H26: -2.89 | I26: 166.39 | J26: 30350.5 | K26: 30516.89 | L26: 328.66
A27: 2025-02 | B27: February 2025 | C27: 947159514 | D27: 166.39 | E27: 3019.94 | F27: 56.61 | G27: -2959.01 | H27: -4.81 | I27: 165.9 | J27: 32447.95 | K27: 32613.85 | L27: 378.26 | N27: 1.26
A28: 2025-03 | B28: March 2025 | C28: 947159514 | D28: 165.9 | E28: 1153.59 | F28: 49.06 | G28: -1047.26 | H28: -1.27 | I28: 221.9 | J28: 32636.19 | K28: 32858.09 | L28: 327.98
A29: 2025-04 | B29: April 2025 | C29: 947159514 | D29: 221.9 | E29: 1350.35 | F29: 45.77 | G29: -968.83 | H29: -4.23 | I29: 553.42 | J29: 33470.83 | K29: 34024.25 | L29: 307.57 | N29: -374.77 | O29: -5.21
A30: 2025-05 | B30: May 2025 | C30: 947159514 | D30: 553.42 | E30: 910.01 | F30: 81.51 | G30: -1234.65 | H30: -3.4 | I30: 143.87 | J30: 34854.36 | K30: 34998.23 | L30: 544.35 | N30: -115.81
A31: 2025-06 | B31: June 2025 | C31: 947159514 | D31: 143.87 | E31: 1189.8 | F31: 55.51 | G31: -1235.88 | H31: -4.86 | I31: 37.42 | J31: 36557.37 | K31: 36594.79 | L31: 371.09 | N31: -16.62 | O31: 1.96
A32: 2025-07 | B32: July 2025 | C32: 947159514 | D32: 37.42 | E32: 1077.65 | F32: 59.21 | G32: -645.4 | H32: -13.45 | I32: 397.01 | J32: 37319 | K32: 37716.01 | L32: 396.17 | N32: -220.87
A33: 2025-08 | B33: August 2025 | C33: 947159514 | D33: 397.01 | E33: 456.87 | F33: 68.35 | G33: -74.46 | H33: -10.17 | I33: 700.9 | J33: 36996.78 | K33: 37697.68 | L33: 456.83 | N33: -23.36
A34: 2025-09 | B34: September 2025 | C34: 947159514 | D34: 700.9 | E34: 376.59 | F34: 56.31 | G34: -395.06 | H34: -0.13 | I34: 625.99 | J34: 37384.71 | K34: 38010.7 | L34: 376.59
A35: 2025-10 | B35: October 2025 | C35: 947159514 | D35: 625.99 | E35: 981.72 | F35: 76.39 | G35: -1407.24 | H35: -2.23 | I35: 121.85 | J35: 38731.5 | K35: 38853.35 | L35: 511.26 | N35: 1.03 | O35: 0.83
A36: 2025-11 | B36: November 2025 | C36: 947159514 | D36: 121.85 | E36: 1522.31 | F36: 53.39 | G36: -1569.11 | H36: -2.23 | I36: 19.43 | J36: 39259.76 | K36: 39279.19 | L36: 357.43
A37: 2025-12 | B37: December 2025 | C37: 947159514 | D37: 19.43 | E37: 2213.6 | F37: 77.68 | G37: -2021.57 | H37: -2.36 | I37: 131.42 | J37: 40924.62 | K37: 41056.04 | L37: 520.13 | N37: 237.74 | O37: -237.74
A38: 2026-01 | B38: January 2026 | C38: 947159514 | D38: 131.42 | E38: 2236.01 | F38: 69.84 | G38: -1999.65 | H38: -2.91 | I38: 295.03 | J38: 42691.28 | K38: 42986.31 | L38: 262.41 | N38: 15.49
A39: 2026-02 | B39: February 2026 | C39: 947159514 | D39: 295.03 | E39: 1755.15 | F39: 47.42 | G39: -1836.45 | H39: -1.92 | I39: 164.39 | J39: 43346.18 | K39: 43510.57 | L39: 317.73
A40: 2026-03 | B40: March 2026 | C40: 947159514 | D40: 164.39 | E40: 445.52 | F40: 44.08 | G40: -424.69 | H40: -4.12 | I40: 137.02 | J40: 42963.77 | K40: 43100.79 | L40: 295.52 | N40: -653.04 | O40: -436.94
A41: 2026-04 | B41: April 2026 | C41: 947159514 | D41: 137.02 | E41: 2917.8 | F41: 44.17 | G41: -1360.96 | H41: -8.66 | I41: 1641.03 | J41: 45674.74 | K41: 47315.77 | L41: 296.62 | N41: -2325.4 | O41: -385.57

Sheet Holdings
A1: Month | B1: Symbol | C1: Description | D1: Quantity | E1: Market Price | F1: Market Value | G1: Cost Price | H1: Unrealized | I1: TD Cost Basis
A2: 2023-01 | B2: *Cash | C2: USD | D2: $-- | F2: 4.02
A3: 2023-01 | B3: MCHI | C3: ISHARES TR MSCI CHINA ETF | D3: 0.29756297 | E3: 53.58 | F3: 15.94 | G3: 48.83 | H3: 1.41 | I3: 14.53
A4: 2023-01 | B4: VNAM | C4: GLOBAL X FDS MSCI VIETNAM ETF | D4: 1 | E4: 16.65 | F4: 16.65 | G4: 15.48 | H4: 1.17 | I4: 15.48
A5: 2023-02 | B5: *Cash | C5: USD | D5: $-- | F5: 0.01
A6: 2023-02 | B6: MCHI | C6: ISHARES TR MSCI CHINA ETF | D6: 1.0845778 | E6: 47.86 | F6: 51.91 | G6: 51.76 | H6: -4.23 | I6: 56.14
A7: 2023-02 | B7: VNAM | C7: GLOBAL X FDS MSCI VIETNAM ETF | D7: 2 | E7: 14.59 | F7: 29.18 | G7: 15.77 | H7: -2.37 | I7: 31.55
A8: 2023-03 | B8: *Cash | C8: USD | D8: $-- | F8: 0.01
A9: 2023-03 | B9: MCHI | C9: ISHARES TR MSCI CHINA ETF | D9: 1.0845778 | E9: 49.89 | F9: 54.11 | G9: 51.76 | H9: -2.03 | I9: 56.14
A10: 2023-03 | B10: VNAM | C10: GLOBAL X FDS MSCI VIETNAM ETF | D10: 2 | E10: 15.59 | F10: 31.17 | G10: 15.77 | H10: -0.38 | I10: 31.55
A11: 2023-04 | B11: *Cash | C11: USD | D11: $-- | F11: 0.01
A12: 2023-04 | B12: MCHI | C12: ISHARES TR MSCI CHINA ETF | D12: 1.0845778 | E12: 47.72 | F12: 51.76 | G12: 51.76 | H12: -4.38 | I12: 56.14
A13: 2023-04 | B13: VNAM | C13: GLOBAL X FDS MSCI VIETNAM ETF | D13: 2 | E13: 15.39 | F13: 30.78 | G13: 15.77 | H13: -0.77 | I13: 31.55
A14: 2023-05 | B14: *Cash | C14: USD | D14: $-- | F14: 0.01
A15: 2023-05 | B15: MCHI | C15: ISHARES TR MSCI CHINA ETF | D15: 1.0845778 | E15: 43.24 | F15: 46.9 | G15: 51.76 | H15: -9.24 | I15: 56.14
A16: 2023-05 | B16: VNAM | C16: GLOBAL X FDS MSCI VIETNAM ETF | D16: 2 | E16: 15.66 | F16: 31.33 | G16: 15.77 | H16: -0.22 | I16: 31.55
A17: 2023-06 | B17: *Cash | C17: USD | D17: $-- | F17: 0.42
A18: 2023-06 | B18: MCHI | C18: ISHARES TR MSCI CHINA ETF | D18: 1.0845778 | E18: 44.74 | F18: 48.52 | G18: 51.76 | H18: -7.61 | I18: 56.14
A19: 2023-06 | B19: VNAM | C19: GLOBAL X FDS MSCI VIETNAM ETF | D19: 2 | E19: 16.61 | F19: 33.21 | G19: 15.77 | H19: 1.66 | I19: 31.55
A20: 2023-07 | B20: *Cash | C20: USD | D20: $-- | F20: 0.48
A21: 2023-07 | B21: MCHI | C21: ISHARES TR MSCI CHINA ETF | D21: 1.0845778 | E21: 49.8 | F21: 54.01 | G21: 51.76 | H21: -2.13 | I21: 56.14
A22: 2023-07 | B22: VNAM | C22: GLOBAL X FDS MSCI VIETNAM ETF | D22: 2 | E22: 18.49 | F22: 36.98 | G22: 15.77 | H22: 5.43 | I22: 31.55
A23: 2023-08 | B23: *Cash | C23: USD | D23: $-- | F23: 0.48
A24: 2023-08 | B24: MCHI | C24: ISHARES TR MSCI CHINA ETF | D24: 1.0845778 | E24: 44.91 | F24: 48.71 | G24: 51.76 | H24: -7.43 | I24: 56.14
A25: 2023-08 | B25: VNAM | C25: GLOBAL X FDS MSCI VIETNAM ETF | D25: 2 | E25: 18.51 | F25: 37.03 | G25: 15.77 | H25: 5.48 | I25: 31.55
A26: 2023-09 | B26: *Cash | C26: USD | D26: $-- | F26: 0.48
A27: 2023-09 | B27: MCHI | C27: ISHARES TR MSCI CHINA ETF | D27: 1.0845778 | E27: 43.29 | F27: 46.95 | G27: 51.76 | H27: -9.19 | I27: 56.14
A28: 2023-09 | B28: VNAM | C28: GLOBAL X FDS MSCI VIETNAM ETF | D28: 2 | E28: 16.75 | F28: 33.49 | G28: 15.77 | H28: 1.94 | I28: 31.55
A29: 2023-10 | B29: *Cash | C29: USD | D29: $-- | F29: 0.48
A30: 2023-10 | B30: MCHI | C30: ISHARES TR MSCI CHINA ETF | D30: 1.0845778 | E30: 41.81 | F30: 45.35 | G30: 51.76 | H30: -10.79 | I30: 56.14
A31: 2023-10 | B31: VNAM | C31: GLOBAL X FDS MSCI VIETNAM ETF | D31: 2 | E31: 14.29 | F31: 28.58 | G31: 15.77 | H31: -2.97 | I31: 31.55
A32: 2023-11 | B32: *Cash | C32: USD | D32: $-- | F32: 0.48
A33: 2023-11 | B33: MCHI | C33: ISHARES TR MSCI CHINA ETF | D33: 1.0845778 | E33: 42.68 | F33: 46.29 | G33: 51.76 | H33: -9.85 | I33: 56.14
A34: 2023-11 | B34: VNAM | C34: GLOBAL X FDS MSCI VIETNAM ETF | D34: 2 | E34: 16.1 | F34: 32.2 | G34: 15.77 | H34: 0.65 | I34: 31.55
A35: 2023-12 | B35: *Cash | C35: USD | D35: $-- | F35: 1.4
A36: 2023-12 | B36: ARM | C36: ARM HOLDINGS PLC SPONSORED ADR | D36: 0.48281391 | E36: 75.15 | F36: 36.28 | G36: 71.1 | H36: 1.95 | I36: 34.33
A37: 2023-12 | B37: MCHI | C37: ISHARES TR MSCI CHINA ETF | D37: 1.802739 | E37: 40.74 | F37: 73.44 | G37: 47.29 | H37: -11.81 | I37: 85.26
A38: 2023-12 | B38: NDAQ | C38: NASDAQ INC COM | D38: 1.0311636 | E38: 58.14 | F38: 59.95 | G38: 54.23 | H38: 4.03 | I38: 55.92
A39: 2023-12 | B39: VNAM | C39: GLOBAL X FDS MSCI VIETNAM ETF | D39: 2 | E39: 16.58 | F39: 33.16 | G39: 15.77 | H39: 1.61 | I39: 31.55
A40: 2024-01 | B40: *Cash | C40: USD | D40: $-- | F40: 7.97
A41: 2024-01 | B41: ARM | C41: ARM HOLDINGS PLC SPONSORED ADR | D41: 0.48281391 | E41: 70.67 | F41: 34.12 | G41: 71.1 | H41: -0.21 | I41: 34.33
A42: 2024-01 | B42: MCHI | C42: ISHARES TR MSCI CHINA ETF | D42: 1.802739 | E42: 36.54 | F42: 65.87 | G42: 47.29 | H42: -19.39 | I42: 85.26
A43: 2024-01 | B43: NDAQ | C43: NASDAQ INC COM | D43: 1.0311636 | E43: 57.77 | F43: 59.57 | G43: 54.23 | H43: 3.65 | I43: 55.92
A44: 2024-01 | B44: VNAM | C44: GLOBAL X FDS MSCI VIETNAM ETF | D44: 4 | E44: 16.36 | F44: 65.44 | G44: 16.27 | H44: 0.37 | I44: 65.07
A45: 2024-02 | B45: *Cash | C45: USD | D45: $-- | F45: 7.97
A46: 2024-02 | B46: ARM | C46: ARM HOLDINGS PLC SPONSORED ADR | D46: 0.48281391 | E46: 141.04 | F46: 68.1 | G46: 71.1 | H46: 33.77 | I46: 34.33
A47: 2024-02 | B47: MCHI | C47: ISHARES TR MSCI CHINA ETF | D47: 1.802739 | E47: 38.99 | F47: 70.29 | G47: 47.29 | H47: -14.97 | I47: 85.26
A48: 2024-02 | B48: NDAQ | C48: NASDAQ INC COM | D48: 1.0311636 | E48: 56.2 | F48: 57.95 | G48: 54.23 | H48: 2.03 | I48: 55.92
A49: 2024-02 | B49: SHV | C49: ISHARES TR SHORT TREAS BD | D49: 1.2816789 | E49: 110.53 | F49: 141.66 | G49: 110.17 | H49: 0.46 | I49: 141.2
A50: 2024-02 | B50: VNAM | C50: GLOBAL X FDS MSCI VIETNAM ETF | D50: 4 | E50: 17.39 | F50: 69.56 | G50: 16.27 | H50: 4.49 | I50: 65.07
A51: 2024-03 | B51: *Cash | C51: USD | D51: $-- | F51: 9.01
A52: 2024-03 | B52: ARM | C52: ARM HOLDINGS PLC SPONSORED ADR | D52: 0.48281391 | E52: 124.99 | F52: 60.35 | G52: 71.1 | H52: 26.02 | I52: 34.33
A53: 2024-03 | B53: MCHI | C53: ISHARES TR MSCI CHINA ETF | D53: 1.802739 | E53: 39.73 | F53: 71.62 | G53: 47.29 | H53: -13.64 | I53: 85.26
A54: 2024-03 | B54: NDAQ | C54: NASDAQ INC COM | D54: 1.0311636 | E54: 63.1 | F54: 65.07 | G54: 54.23 | H54: 9.15 | I54: 55.92
A55: 2024-03 | B55: QYLD | C55: GLOBAL X FDS NASDAQ 100 COVER | D55: 2.3240612 | E55: 17.91 | F55: 41.62 | G55: 17.98 | H55: -0.15 | I55: 41.77
A56: 2024-03 | B56: SGOV | C56: ISHARES TR 0-3 MNTH TREASRY | D56: 0.69302594 | E56: 100.71 | F56: 69.79 | G56: 100.46 | H56: 0.17 | I56: 69.62
A57: 2024-03 | B57: SHV | C57: ISHARES TR SHORT TREAS BD | D57: 3.0663912 | E57: 110.54 | F57: 338.96 | G57: 110.2 | H57: 1.05 | I57: 337.91
A58: 2024-03 | B58: VNAM | C58: GLOBAL X FDS MSCI VIETNAM ETF | D58: 4 | E58: 17.86 | F58: 71.44 | G58: 16.27 | H58: 6.37 | I58: 65.07
A59: 2024-04 | B59: *Cash | C59: USD | D59: $-- | F59: 24.02
A60: 2024-04 | B60: ARM | C60: ARM HOLDINGS PLC SPONSORED ADR | D60: 0.48281391 | E60: 101.21 | F60: 48.87 | G60: 71.1 | H60: 14.54 | I60: 34.33
A61: 2024-04 | B61: KLIP | C61: KRANESHARES TRUST KRANESHARES CN | D61: 15 | E61: 14.49 | F61: 217.35 | G61: 14.55 | H61: -0.9 | I61: 218.25
A62: 2024-04 | B62: MCHI | C62: ISHARES TR MSCI CHINA ETF | D62: 1.802739 | E62: 41.87 | F62: 75.48 | G62: 47.29 | H62: -9.78 | I62: 85.26
A63: 2024-04 | B63: NDAQ | C63: NASDAQ INC COM | D63: 1.0311636 | E63: 59.85 | F63: 61.72 | G63: 54.23 | H63: 5.8 | I63: 55.92
A64: 2024-04 | B64: QYLD | C64: GLOBAL X FDS NASDAQ 100 COVER | D64: 17.541234 | E64: 17.41 | F64: 305.39 | G64: 17.94 | H64: -9.3 | I64: 314.69
A65: 2024-04 | B65: RYLD | C65: GLOBAL X FDS RUSSELL 2000 | D65: 12.825266 | E65: 16.32 | F65: 209.31 | G65: 16.43 | H65: -1.35 | I65: 210.65
A66: 2024-04 | B66: SGOV | C66: ISHARES TR 0-3 MNTH TREASRY | D66: 0.69302594 | E66: 100.7 | F66: 69.79 | G66: 100.46 | H66: 0.17 | I66: 69.62
A67: 2024-04 | B67: SHV | C67: ISHARES TR SHORT TREAS BD | D67: 20.420107 | E67: 110.47 | F67: 2255.81 | G67: 110.08 | H67: 7.95 | I67: 2247.86
A68: 2024-04 | B68: THW | C68: ABRDN WORLD HEALTHCARE FUND BEN INT SHS | D68: 36 | E68: 12.77 | F68: 459.72 | G68: 13.06 | H68: -10.3 | I68: 470.02
A69: 2024-04 | B69: VNAM | C69: GLOBAL X FDS MSCI VIETNAM ETF | D69: 4 | E69: 15.96 | F69: 63.83 | G69: 16.27 | H69: -1.24 | I69: 65.07
A70: 2024-05 | B70: *Cash | C70: USD | D70: $-- | F70: 41.08
A71: 2024-05 | B71: ARM | C71: ARM HOLDINGS PLC SPONSORED ADR | D71: 0.48281391 | E71: 120.52 | F71: 58.19 | G71: 71.1 | H71: 23.86 | I71: 34.33
A72: 2024-05 | B72: FLTR | C72: VANECK ETF TRUST IG FLOATING RATE | D72: 38.140942 | E72: 25.52 | F72: 973.36 | G72: 25.37 | H72: 5.91 | I72: 967.44
A73: 2024-05 | B73: KLIP | C73: KRANESHARES TRUST KRANESHARES CN | D73: 38 | E73: 13.96 | F73: 530.48 | G73: 14.44 | H73: -18.21 | I73: 548.69
A74: 2024-05 | B74: MCHI | C74: ISHARES TR MSCI CHINA ETF | D74: 1.802739 | E74: 43.82 | F74: 79 | G74: 47.29 | H74: -6.26 | I74: 85.26
A75: 2024-05 | B75: NDAQ | C75: NASDAQ INC COM | D75: 1.0311636 | E75: 59.03 | F75: 60.87 | G75: 54.23 | H75: 4.95 | I75: 55.92
A76: 2024-05 | B76: PFRL | C76: PGIM ETF TR FLOATING RT INC | D76: 4 | E76: 50.85 | F76: 203.38 | G76: 50.41 | H76: 1.75 | I76: 201.63
A77: 2024-05 | B77: QYLD | C77: GLOBAL X FDS NASDAQ 100 COVER | D77: 17.541234 | E77: 17.51 | F77: 307.15 | G77: 17.94 | H77: -7.55 | I77: 314.69
A78: 2024-05 | B78: RYLD | C78: GLOBAL X FDS RUSSELL 2000 | D78: 12.825266 | E78: 16.27 | F78: 208.67 | G78: 16.43 | H78: -1.99 | I78: 210.65
A79: 2024-05 | B79: SGOV | C79: ISHARES TR 0-3 MNTH TREASRY | D79: 11.969197 | E79: 100.75 | F79: 1205.9 | G79: 100.31 | H79: 5.28 | I79: 1200.62
A80: 2024-05 | B80: SHV | C80: ISHARES TR SHORT TREAS BD | D80: 29.590336 | E80: 110.51 | F80: 3270.03 | G80: 110.06 | H80: 13.17 | I80: 3256.86
A81: 2024-05 | B81: THW | C81: ABRDN WORLD HEALTHCARE FUND BEN INT SHS | D81: 39 | E81: 12.84 | F81: 500.76 | G81: 13.03 | H81: -7.6 | I81: 508.36
A82: 2024-05 | B82: VNAM | C82: GLOBAL X FDS MSCI VIETNAM ETF | D82: 4 | E82: 16.46 | F82: 65.84 | G82: 16.27 | H82: 0.77 | I82: 65.07
A83: 2024-06 | B83: *Cash | C83: USD | D83: $-- | F83: 42.26
A84: 2024-06 | B84: ARM | C84: ARM HOLDINGS PLC SPONSORED ADS | D84: 0.48281391 | E84: 163.62 | F84: 79 | G84: 71.1 | H84: 44.67 | I84: 34.33
A85: 2024-06 | B85: FLTR | C85: VANECK ETF TRUST IG FLOATING RATE | D85: 46.723644 | E85: 25.51 | F85: 1191.92 | G85: 25.37 | H85: 6.48 | I85: 1185.44
A86: 2024-06 | B86: GOOY | C86: TIDAL TR II YIELDMAX GOOGL | D86: 12 | E86: 18.39 | F86: 220.72 | G86: 18.16 | H86: 2.84 | I86: 217.88
A87: 2024-06 | B87: ICLO | C87: POWERSHARES ACTIVELY MANAGED AAA CLO FLTNG RT | D87: 9 | E87: 25.68 | F87: 231.08 | G87: 25.64 | H87: 0.32 | I87: 230.76
A88: 2024-06 | B88: KLIP | C88: KRANESHARES TRUST KRANESHARES CN | D88: 50 | E88: 12.88 | F88: 644 | G88: 14.31 | H88: -71.61 | I88: 715.61
A89: 2024-06 | B89: MCHI | C89: ISHARES TR MSCI CHINA ETF | D89: 1.802739 | E89: 42.17 | F89: 76.02 | G89: 47.29 | H89: -9.24 | I89: 85.26
A90: 2024-06 | B90: NDAQ | C90: NASDAQ INC COM | D90: 1.0311636 | E90: 60.26 | F90: 62.14 | G90: 54.23 | H90: 6.22 | I90: 55.92
A91: 2024-06 | B91: PFRL | C91: PGIM ETF TR FLOATING RT INC | D91: 6 | E91: 50.55 | F91: 303.3 | G91: 50.43 | H91: 0.74 | I91: 302.55
A92: 2024-06 | B92: QYLD | C92: GLOBAL X FDS NASDAQ 100 COVER | D92: 17.541234 | E92: 17.67 | F92: 309.95 | G92: 17.94 | H92: -4.74 | I92: 314.69
A93: 2024-06 | B93: RYLD | C93: GLOBAL X FDS RUSSELL 2000 | D93: 14.175986 | E93: 16.03 | F93: 227.24 | G93: 16.41 | H93: -5.37 | I93: 232.61
A94: 2024-06 | B94: SGOV | C94: ISHARES TR 0-3 MNTH TREASRY | D94: 16.524166 | E94: 100.71 | F94: 1664.15 | G94: 100.31 | H94: 6.53 | I94: 1657.62
A95: 2024-06 | B95: SHV | C95: ISHARES TR SHORT TREAS BD | D95: 35.523463 | E95: 110.5 | F95: 3925.34 | G95: 110.06 | H95: 15.48 | I95: 3909.86
... A98: 2024-06 | B98: VRIG | C98: POWERSHARES ACTIVELY MANAGED VAR RATE INVT | D98: 6.5244911 | E98: 25.14 | F98: 164.03 | G98: 25.1 | H98: 0.28 | I98: 163.74
A99: 2024-07 | B99: *Cash | C99: USD | D99: $-- | F99: 7399.11
A100: 2024-07 | B100: ARM | C100: ARM HOLDINGS PLC SPONSORED ADS | D100: 0.48281391 | E100: 144.17 | F100: 69.61 | G100: 71.1 | H100: 35.28 | I100: 34.33
A101: 2024-07 | B101: CAG | C101: CONAGRA BRANDS INC COM | D101: 5.5731407 | E101: 30.32 | F101: 168.98 | G101: 30.46 | H101: -0.75 | I101: 169.73
A102: 2024-07 | B102: CONY | C102: TIDAL TR II YIELDMAX COIN OP | D102: 18 | E102: 18.45 | F102: 332.1 | G102: 20.9 | H102: -44.11 | I102: 376.21
...

Sheet Transactions
A1: Month | B1: Trade Date | C1: Entry Type | D1: Side | E1: Symbol | F1: Description | G1: Quantity | H1: Price | I1: Amount | J1: Commission
A2: 2023-01 | B2: 01/03/2023 | C2: Trade Entry | D2: buy | E2: MCHI | G2: 0.29756297 | H2: 48.83 | I2: -14.53
A3: 2023-01 | B3: 01/03/2023 | C3: Trade Entry | D3: buy | E3: VNAM | G3: 1 | H3: 15.48 | I3: -15.48 | J3: 0.02
A4: 2023-02 | B4: 02/03/2023 | C4: Trade Entry | D4: buy | E4: MCHI | G4: 0.42331845 | H4: 52.87 | I4: -22.38
A5: 2023-02 | B5: 02/03/2023 | C5: Trade Entry | D5: buy | E5: VNAM | G5: 1 | H5: 16.07 | I5: -16.07 | J5: 0.02
A6: 2023-02 | B6: 02/03/2023 | C6: Trade Entry | D6: buy | E6: MCHI | G6: 0.36369638 | H6: 52.87 | I6: -19.23 | J6: 0.03
A7: 2023-12 | B7: 12/13/2023 | C7: Trade Entry | D7: buy | E7: NDAQ | G7: 1.0311636 | H7: 54.23 | I7: -55.92
A8: 2023-12 | B8: 12/21/2023 | C8: Trade Entry | D8: buy | E8: ARM | G8: 0.48281391 | H8: 71.1 | I8: -34.33 | J8: 0.06
A9: 2023-12 | B9: 12/28/2023 | C9: Trade Entry | D9: buy | E9: MCHI | G9: 0.71816119 | H9: 40.55 | I9: -29.12 | J9: 0.05
A10: 2024-01 | B10: 01/08/2024 | C10: Trade Entry | D10: buy | E10: VNAM | G10: 2 | H10: 16.76 | I10: -33.52
A11: 2024-02 | B11: 02/01/2024 | C11: Trade Entry | D11: buy | E11: SHV | G11: 1.2816789 | H11: 110.17 | I11: -141.2
A12: 2024-03 | B12: 03/07/2024 | C12: Trade Entry | D12: buy | E12: SHV | G12: 0.50908365 | H12: 110.2 | I12: -56.1
A13: 2024-03 | B13: 03/08/2024 | C13: Trade Entry | D13: buy | E13: SHV | G13: 1.2756287 | H13: 110.23 | I13: -140.61 | J13: 0.23
A14: 2024-03 | B14: 03/12/2024 | C14: Trade Entry | D14: buy | E14: QYLD | G14: 1 | H14: 17.98 | I14: -17.98
A15: 2024-03 | B15: 03/12/2024 | C15: Trade Entry | D15: buy | E15: QYLD | G15: 1.3240612 | H15: 17.98 | I15: -23.8 | J15: 0.07
A16: 2024-03 | B16: 03/12/2024 | C16: Trade Entry | D16: buy | E16: SGOV | G16: 0.69302594 | H16: 100.46 | I16: -69.62 | J16: 0.11
A17: 2024-04 | B17: 04/01/2024 | C17: Trade Entry | D17: buy | E17: QYLD | G17: 14 | H17: 17.94 | I17: -251.09
A18: 2024-04 | B18: 04/01/2024 | C18: Trade Entry | D18: buy | E18: QYLD | G18: 1.2171731 | H18: 17.94 | I18: -21.83
A19: 2024-04 | B19: 04/01/2024 | C19: Trade Entry | D19: buy | E19: SHV | G19: 16 | H19: 110.06 | I19: -1760.96
A20: 2024-04 | B20: 04/01/2024 | C20: Trade Entry | D20: buy | E20: SHV | G20: 1.3537162 | H20: 110.06 | I20: -148.99
A21: 2024-04 | B21: 04/01/2024 | C21: Trade Entry | D21: buy | E21: THW | G21: 36 | H21: 13.06 | I21: -470.02
A22: 2024-04 | B22: 04/18/2024 | C22: Trade Entry | D22: buy | E22: KLIP | G22: 15 | H22: 14.55 | I22: -218.25
A23: 2024-04 | B23: 04/29/2024 | C23: Trade Entry | D23: buy | E23: RYLD | G23: 11 | H23: 16.43 | I23: -180.68
A24: 2024-04 | B24: 04/29/2024 | C24: Trade Entry | D24: buy | E24: RYLD | G24: 1.8252664 | H24: 16.43 | I24: -29.98 | J24: 0.34
A25: 2024-05 | B25: 05/01/2024 | C25: Trade Entry | D25: buy | E25: FLTR | G25: 37 | H25: 25.37 | I25: -938.51
A26: 2024-05 | B26: 05/01/2024 | C26: Trade Entry | D26: buy | E26: FLTR | G26: 1.1409422 | H26: 25.37 | I26: -28.94 | J26: 1.55
A27: 2024-05 | B27: 05/01/2024 | C27: Trade Entry | D27: buy | E27: KLIP | G27: 15 | H27: 14.52 | I27: -217.73 | J27: 0.35
A28: 2024-05 | B28: 05/01/2024 | C28: Trade Entry | D28: buy | E28: SGOV | G28: 10 | H28: 100.3 | I28: -1003
A29: 2024-05 | B29: 05/01/2024 | C29: Trade Entry | D29: buy | E29: SGOV | G29: 1.2761715 | H29: 100.3 | I29: -128
A30: 2024-05 | B30: 05/01/2024 | C30: Trade Entry | D30: buy | E30: SHV | G30: 8 | H30: 110.03 | I30: -880.24
A31: 2024-05 | B31: 05/01/2024 | C31: Trade Entry | D31: buy | E31: SHV | G31: 1.1702284 | H31: 110.03 | I31: -128.76
A32: 2024-05 | B32: 05/01/2024 | C32: Trade Entry | D32: buy | E32: THW | G32: 3 | H32: 12.78 | I32: -38.34 | J32: 0.06
A33: 2024-05 | B33: 05/02/2024 | C33: Trade Entry | D33: buy | E33: PFRL | G33: 4 | H33: 50.41 | I33: -201.63 | J33: 0.32
A34: 2024-05 | B34: 05/30/2024 | C34: Trade Entry | D34: buy | E34: KLIP | G34: 8 | H34: 14.09 | I34: -112.72 | J34: 0.18
A35: 2024-06 | B35: 06/03/2024 | C35: Trade Entry | D35: buy | E35: FLTR | G35: 7 | H35: 25.4 | I35: -177.8
A36: 2024-06 | B36: 06/03/2024 | C36: Trade Entry | D36: buy | E36: FLTR | G36: 1.5827021 | H36: 25.4 | I36: -40.2
A37: 2024-06 | B37: 06/03/2024 | C37: Trade Entry | D37: buy | E37: GOOY | G37: 6 | H37: 18.14 | I37: -108.84 | J37: 0.17
A38: 2024-06 | B38: 06/03/2024 | C38: Trade Entry | D38: buy | E38: KLIP | G38: 8 | H38: 13.93 | I38: -111.44 | J38: 0.18
A39: 2024-06 | B39: 06/03/2024 | C39: Trade Entry | D39: buy | E39: PFRL | G39: 2 | H39: 50.46 | I39: -100.92 | J39: 0.16
A40: 2024-06 | B40: 06/03/2024 | C40: Trade Entry | D40: buy | E40: RYLD | G40: 1.3507196 | H40: 16.26 | I40: -21.96 | J40: 0.04
A41: 2024-06 | B41: 06/03/2024 | C41: Trade Entry | D41: buy | E41: SGOV | G41: 3 | H41: 100.33 | I41: -300.99
A42: 2024-06 | B42: 06/03/2024 | C42: Trade Entry | D42: buy | E42: SGOV | G42: 1.5549686 | H42: 100.33 | I42: -156.01
A43: 2024-06 | B43: 06/03/2024 | C43: Trade Entry | D43: buy | E43: SHV | G43: 4 | H43: 110.06 | I43: -440.24
A44: 2024-06 | B44: 06/03/2024 | C44: Trade Entry | D44: buy | E44: SHV | G44: 1.9331274 | H44: 110.06 | I44: -212.76
A45: 2024-06 | B45: 06/24/2024 | C45: Trade Entry | D45: buy | E45: GOOY | G45: 6 | H45: 18.17 | I45: -109.04 | J45: 0.17
A46: 2024-06 | B46: 06/24/2024 | C46: Trade Entry | D46: buy | E46: ICLO | G46: 9 | H46: 25.64 | I46: -230.76 | J46: 0.37
A47: 2024-06 | B47: 06/24/2024 | C47: Trade Entry | D47: buy | E47: KLIP | G47: 4 | H47: 13.87 | I47: -55.48 | J47: 0.09
A48: 2024-06 | B48: 06/24/2024 | C48: Trade Entry | D48: buy | E48: VRIG | G48: 1.5244911 | H48: 25.1 | I48: -38.26 | J48: 0.26
A49: 2024-06 | B49: 06/24/2024 | C49: Trade Entry | D49: buy | E49: VRIG | G49: 5 | H49: 25.1 | I49: -125.48
A50: 2024-07 | B50: 07/01/2024 | C50: Trade Entry | D50: buy | E50: CONY | G50: 18 | H50: 20.9 | I50: -376.21 | J50: 0.6
A51: 2024-07 | B51: 07/01/2024 | C51: Trade Entry | D51: buy | E51: FLTR | G51: 1.4847351 | H51: 25.39 | I51: -37.69
A52: 2024-07 | B52: 07/01/2024 | C52: Trade Entry | D52: buy | E52: FLTR | G52: 6 | H52: 25.39 | I52: -152.31
A53: 2024-07 | B53: 07/01/2024 | C53: Trade Entry | D53: buy | E53: JAAA | G53: 1.6400372 | H53: 50.63 | I53: -83.03 | J53: 0.46
A54: 2024-07 | B54: 07/01/2024 | C54: Trade Entry | D54: buy | E54: JAAA | G54: 4 | H54: 50.63 | I54: -202.51
A55: 2024-07 | B55: 07/01/2024 | C55: Trade Entry | D55: buy | E55: NVDY | G55: 2 | H55: 29.02 | I55: -58.04
A56: 2024-07 | B56: 07/01/2024 | C56: Trade Entry | D56: buy | E56: NVDY | G56: 1.2684356 | H56: 29.02 | I56: -36.81 | J56: 0.15
A57: 2024-07 | B57: 07/01/2024 | C57: Trade Entry | D57: buy | E57: PFRL | G57: 4 | H57: 50.33 | I57: -201.32 | J57: 0.32
A58: 2024-07 | B58: 07/01/2024 | C58: Trade Entry | D58: buy | E58: SGOV | G58: 1 | H58: 100.31 | I58: -100.31
A59: 2024-07 | B59: 07/01/2024 | C59: Trade Entry | D59: buy | E59: SGOV | G59: 1.7913486 | H59: 100.31 | I59: -179.69
A60: 2024-07 | B60: 07/01/2024 | C60: Trade Entry | D60: buy | E60: SHV | G60: 2 | H60: 110.05 | I60: -220.1
A61: 2024-07 | B61: 07/01/2024 | C61: Trade Entry | D61: buy | E61: SHV | G61: 1.4529786 | H61: 110.05 | I61: -159.9
A62: 2024-07 | B62: 07/23/2024 | C62: Trade Entry | D62: buy | E62: ICLO | G62: 35 | H62: 25.65 | I62: -897.58
A63: 2024-07 | B63: 07/23/2024 | C63: Trade Entry | D63: buy | E63: ICLO | G63: 1.5566387 | H63: 25.65 | I63: -39.92 | J63: 1.5
A64: 2024-07 | B64: 07/23/2024 | C64: Trade Entry | D64: buy | E64: VRIG | G64: 17 | H64: 25.09 | I64: -426.53
A65: 2024-07 | B65: 07/23/2024 | C65: Trade Entry | D65: buy | E65: VRIG | G65: 1.6628271 | H65: 25.09 | I65: -41.72 | J65: 0.75
A66: 2024-07 | B66: 07/26/2024 | C66: Trade Entry | D66: buy | E66: KLIP | G66: 21 | H66: 12.96 | I66: -272.16
A67: 2024-07 | B67: 07/26/2024 | C67: Trade Entry | D67: buy | E67: KLIP | G67: 1.3410597 | H67: 12.96 | I67: -17.38 | J67: 0.46
A68: 2024-07 | B68: 07/30/2024 | C68: Trade Entry | D68: buy | E68: CAG | G68: 4 | H68: 30.46 | I68: -121.82
A69: 2024-07 | B69: 07/30/2024 | C69: Trade Entry | D69: buy | E69: CAG | G69: 1.5731407 | H69: 30.46 | I69: -47.91 | J69: 0.27
A70: 2024-07 | B70: 07/30/2024 | C70: Trade Entry | D70: buy | E70: NVO | G70: 1.3229357 | H70: 128.3 | I70: -169.73 | J70: 0.27
A71: 2024-07 | B71: 07/30/2024 | C71: Trade Entry | D71: buy | E71: PBJ | G71: 2 | H71: 45.85 | I71: -91.7
A72: 2024-07 | B72: 07/30/2024 | C72: Trade Entry | D72: buy | E72: PBJ | G72: 1.7018873 | H72: 45.85 | I72: -78.03 | J72: 0.27
A73: 2024-08 | B73: 08/01/2024 | C73: Trade Entry | D73: buy | E73: FLTR | G73: 18 | H73: 25.38 | I73: -456.84
A74: 2024-08 | B74: 08/01/2024 | C74: Trade Entry | D74: buy | E74: FLTR | G74: 1.2277384 | H74: 25.38 | I74: -31.16
A75: 2024-08 | B75: 08/01/2024 | C75: Trade Entry | D75: buy | E75: JAAA | G75: 22 | H75: 50.7 | I75: -1115.33
A76: 2024-08 | B76: 08/01/2024 | C76: Trade Entry | D76: buy | E76: JAAA | G76: 1.0610137 | H76: 50.7 | I76: -53.79 | J76: 1.88
A77: 2024-08 | B77: 08/01/2024 | C77: Trade Entry | D77: buy | E77: PFRL | G77: 19 | H77: 50.35 | I77: -956.65 | J77: 1.55
A78: 2024-08 | B78: 08/01/2024 | C78: Trade Entry | D78: buy | E78: SGOV | G78: 13 | H78: 100.3 | I78: -1303.86
A79: 2024-08 | B79: 08/01/2024 | C79: Trade Entry | D79: buy | E79: SGOV | G79: 1.5866891 | H79: 100.3 | I79: -159.14
A80: 2024-08 | B80: 08/01/2024 | C80: Trade Entry | D80: buy | E80: SHV | G80: 7 | H80: 110.09 | I80: -770.61
A81: 2024-08 | B81: 08/01/2024 | C81: Trade Entry | D81: buy | E81: SHV | G81: 1.8657096 | H81: 110.09 | I81: -205.39
A82: 2024-08 | B82: 08/12/2024 | C82: Trade Entry | D82: buy | E82: GOOY | G82: 8 | H82: 15.54 | I82: -124.32 | J82: 0.2
A83: 2024-08 | B83: 08/12/2024 | C83: Trade Entry | D83: buy | E83: NVDY | G83: 0.28035805 | H83: 23.68 | I83: -6.64 | J83: 0.01
A84: 2024-08 | B84: 08/26/2024 | C84: Trade Entry | D84: buy | E84: SVOL | G84: 14 | H84: 22.52 | I84: -315.21
A85: 2024-08 | B85: 08/26/2024 | C85: Trade Entry | D85: buy | E85: SVOL | G85: 1.5203198 | H85: 22.52 | I85: -34.23 | J85: 0.56
A86: 2024-08 | B86: 08/30/2024 | C86: Trade Entry | D86: buy | E86: KLIP | G86: 19 | H86: 12.16 | I86: -231.01
A87: 2024-08 | B87: 08/30/2024 | C87: Trade Entry | D87: buy | E87: KLIP | G87: 1.5290092 | H87: 12.16 | I87: -18.59 | J87: 0.4
A88: 2024-08 | B88: 08/30/2024 | C88: Trade Entry | D88: buy | E88: MSTY | G88: 11 | H88: 23 | I88: -253 | J88: 0.41
A89: 2024-08 | B89: 08/30/2024 | C89: Trade Entry | D89: buy | E89: O | G89: 1 | H89: 61.86 | I89: -61.86
A90: 2024-08 | B90: 08/30/2024 | C90: Trade Entry | D90: buy | E90: O | G90: 1.7437819 | H90: 61.86 | I90: -107.87 | J90: 0.27
A91: 2024-09 | B91: 09/23/2024 | C91: Trade Entry | D91: buy | E91: ICLO | G91: 6 | H91: 25.6 | I91: -153.6
A92: 2024-09 | B92: 09/23/2024 | C92: Trade Entry | D92: buy | E92: ICLO | G92: 1.109388 | H92: 25.6 | I92: -28.4
A93: 2024-10 | B93: 10/03/2024 | C93: Trade Entry | D93: buy | E93: CONY | G93: 21 | H93: 12.3 | I93: -258.29
A94: 2024-10 | B94: 10/03/2024 | C94: Trade Entry | D94: buy | E94: CONY | G94: 1.4854021 | H94: 12.3 | I94: -18.27 | J94: 0.44
A95: 2024-10 | B95: 10/03/2024 | C95: Trade Entry | D95: buy | E95: FBY | G95: 9 | H95: 20.22 | I95: -181.98 | J95: 0.29
A96: 2024-10 | B96: 10/03/2024 | C96: Trade Entry | D96: buy | E96: FLTR | G96: 4 | H96: 25.36 | I96: -101.43
A97: 2024-10 | B97: 10/03/2024 | C97: Trade Entry | D97: buy | E97: FLTR | G97: 1.4815604 | H97: 25.36 | I97: -37.57
A98: 2024-10 | B98: 10/03/2024 | C98: Trade Entry | D98: buy | E98: GOOY | G98: 9 | H98: 15.16 | I98: -136.44 | J98: 0.22
A99: 2024-10 | B99: 10/03/2024 | C99: Trade Entry | D99: buy | E99: JAAA | G99: 1 | H99: 50.66 | I99: -50.66
A100: 2024-10 | B100: 10/03/2024 | C100: Trade Entry | D100: buy | E100: JAAA | G100: 1.7395424 | H100: 50.66 | I100: -88.12 | J100: 0.22
...

Sheet Income
A1: Month | B1: Trade Date | C1: Entry Type | D1: Symbol | E1: Description | F1: Net Amt
A2: 2023-01 | B2: 01/03/2023 | C2: Journal Entry(Cash) | E2: ID: b4729546-67b3-483d-8c77-152913c7a89a - STKSWI20230103054511111950 | F2: 14.53
A3: 2023-01 | B3: 01/03/2023 | C3: Journal Entry(Cash) | E3: ID: e2816bfb-b30f-4f60-81e2-62052d38dfc8 - STKSWI20230103025053112708 | F3: 14.52
A4: 2023-01 | B4: 01/03/2023 | C4: Journal Entry(Cash) | E4: ID: 8afec0a1-64d2-4776-b0bb-06882c1a57fd - STKSWI20230103025331112736 | F4: 5
A5: 2023-02 | B5: 02/03/2023 | C5: Journal Entry(Cash) | E5: ID: b45e44a3-b88d-4ef0-84c6-eae79ad816d0 - STKSWI20230203052647162913 | F5: 22.38
A6: 2023-02 | B6: 02/03/2023 | C6: Journal Entry(Cash) | E6: ID: cb2f3f40-0d7d-4fc6-bf07-a123bb06ef44 - STKSWI20230203052813162918 | F6: 13.43
A7: 2023-02 | B7: 02/03/2023 | C7: Journal Entry(Cash) | E7: ID: b63c5274-577d-4864-ba79-59552edf0cf0 - STKSWI20230203053002162922 | F7: 5.97
A8: 2023-02 | B8: 02/03/2023 | C8: Journal Entry(Cash) | E8: ID: 3857e917-92dd-48f5-a477-8358503b48e0 - STKSWI20230203053121162925 | F8: 11.94
A9: 2023-06 | B9: 06/13/2023 | C9: Dividends | D9: MCHI | E9: Cash DIV @ 0.091277, Pos QTY: 1.084577801, Rec Date: 2023-06-08 | F9: 0.1
A10: 2023-06 | B10: 06/13/2023 | C10: Div. Adj(NRA Withheld) | D10: MCHI | E10: DIV tax withholding on $0.37 at 15% for tax country THA; w8w9: w8 | F10: -0.05
A11: 2023-06 | B11: 06/13/2023 | C11: Dividends | D11: MCHI | E11: Cash DIV @ 0.337912, Pos QTY: 1.084577801, Rec Date: 2023-06-08 | F11: 0.37
A12: 2023-06 | B12: 06/13/2023 | C12: Div. Adj(NRA Withheld) | D12: MCHI | E12: DIV tax withholding on $0.1 at 15% for tax country THA; w8w9: w8 | F12: -0.01
A13: 2023-07 | B13: 07/10/2023 | C13: Dividends | D13: VNAM | E13: Cash DIV @ 0.029971, Pos QTY: 2, Rec Date: 2023-06-30 | F13: 0.06
A14: 2023-12 | B14: 12/12/2023 | C14: Journal Entry(Cash) | E14: ID: 5eb026bc-02b2-420a-8163-637c02d4ab07 - STKSWI20231213031023999052 | F14: 55.92
A15: 2023-12 | B15: 12/21/2023 | C15: Journal Entry(Cash) | E15: ID: 19137a2a-257e-40c7-863f-99bed01e969b - STKSWI20231221043059031020 | F15: 34.39
A16: 2023-12 | B16: 12/27/2023 | C16: Dividends | D16: MCHI | E16: Cash DIV @ 0.994126, Pos QTY: 1.084577801, Rec Date: 2023-12-21 | F16: 1.08
A17: 2023-12 | B17: 12/27/2023 | C17: Div. Adj(NRA Withheld) | D17: MCHI | E17: DIV tax withholding on $1.08 at 15% for tax country THA; w8w9: w8 | F17: -0.16
A18: 2023-12 | B18: 12/28/2023 | C18: Journal Entry(Cash) | E18: ID: 09c37510-9bc2-44e1-9d1b-62867750d5fb - STKSWI20231228053645057992 | F18: 29.17
A19: 2024-01 | B19: 01/08/2024 | C19: Div. Adj(NRA Withheld) | D19: VNAM | E19: DIV tax withholding on $0.1 at 15% for tax country THA; w8w9: w8 | F19: -0.01
A20: 2024-01 | B20: 01/08/2024 | C20: Dividends | D20: VNAM | E20: Cash DIV @ 0.05168, Pos QTY: 2, Rec Date: 2023-12-29 | F20: 0.1
A21: 2024-01 | B21: 01/08/2024 | C21: Journal Entry(Cash) | E21: ID: e65045d0-447e-4064-83ea-b959ff3c1835 - STKSWI20240108032719103957 | F21: 40
A22: 2024-02 | B22: 02/01/2024 | C22: Journal Entry(Cash) | E22: ID: c0ea41b8-87c9-47da-b9dd-43ae9c62ec85 - STKSWI20240201051107229712 | F22: 141.2
A23: 2024-03 | B23: 03/07/2024 | C23: Dividends | D23: SHV | E23: Cash DIV @ 0.447689, Pos QTY: 1.28167889, Rec Date: 2024-03-04 | F23: 0.57
A24: 2024-03 | B24: 03/07/2024 | C24: Div. Adj(NRA Withheld) | D24: SHV | E24: DIV tax withholding on $0.57 at 15% for tax country THA; w8w9: w8 | F24: -0.08
A25: 2024-03 | B25: 03/07/2024 | C25: Journal Entry(Cash) | E25: ID: c9955775-a483-4de7-aa8d-4f924fec428e - STKSWI20240307055921511775 | F25: 56.1
A26: 2024-03 | B26: 03/08/2024 | C26: Journal Entry(Cash) | E26: ID: b77cd62d-a305-4db7-9248-764b343b42c7 - STKSWI20240308031250520265 | F26: 140.84
A27: 2024-03 | B27: 03/12/2024 | C27: Journal Entry(Cash) | E27: ID: dc34fd94-bff4-43ba-b75d-c6a002a9d1aa - STKSWI20240312052311551772 | F27: 69.73
A28: 2024-03 | B28: 03/12/2024 | C28: Journal Entry(Cash) | E28: ID: 6588f7bc-a372-44a1-bb15-46ef94aa70ca - STKSWI20240312054413551968 | F28: 41.85
A29: 2024-03 | B29: 03/26/2024 | C29: Dividends | D29: QYLD | E29: Cash DIV @ 0.178, Pos QTY: 2.324061196, Rec Date: 2024-03-19 | F29: 0.41
A30: 2024-03 | B30: 03/26/2024 | C30: Div. Adj(NRA Withheld) | D30: QYLD | E30: DIV tax withholding on $0.41 at 15% for tax country THA; w8w9: w8 | F30: -0.06
A31: 2024-03 | B31: 03/28/2024 | C31: Div. Adj(NRA Withheld) | D31: NDAQ | E31: DIV tax withholding on $0.23 at 15% for tax country THA; w8w9: w8 | F31: -0.03
A32: 2024-03 | B32: 03/28/2024 | C32: Dividends | D32: NDAQ | E32: Cash DIV @ 0.22, Pos QTY: 1.031163562, Rec Date: 2024-03-14 | F32: 0.23
A33: 2024-04 | B33: 04/01/2024 | C33: Journal Entry(Cash) | E33: ID: 435c3202-2f87-4370-9069-f79ef62e8401 - STKSWI20240401022927733357 | F33: 1909.95
A34: 2024-04 | B34: 04/01/2024 | C34: Journal Entry(Cash) | E34: ID: 82b7046f-7243-495d-882e-31d1ec6a2aa2 - STKSWI20240401025816735120 | F34: 272.92
A35: 2024-04 | B35: 04/01/2024 | C35: Journal Entry(Cash) | E35: ID: 4432c579-1035-48e6-b68f-0c71585c936f - STKSWI20240401030332735375 | F35: 545.55
A36: 2024-04 | B36: 04/05/2024 | C36: Div. Adj(NRA Withheld) | D36: SGOV | E36: DIV tax withholding on $0.31 at 15% for tax country THA; w8w9: w8 | F36: -0.04
A37: 2024-04 | B37: 04/05/2024 | C37: Div. Adj(NRA Withheld) | D37: SHV | E37: DIV tax withholding on $1.48 at 15% for tax country THA; w8w9: w8 | F37: -0.22
A38: 2024-04 | B38: 04/05/2024 | C38: Dividends | D38: SHV | E38: Cash DIV @ 0.481925, Pos QTY: 3.066391235, Rec Date: 2024-04-02 | F38: 1.48
A39: 2024-04 | B39: 04/05/2024 | C39: Dividends | D39: SGOV | E39: Cash DIV @ 0.449911, Pos QTY: 0.693025941, Rec Date: 2024-04-02 | F39: 0.31
A40: 2024-04 | B40: 04/18/2024 | C40: Journal Entry(Cash) | E40: ID: b3395d97-4841-4216-9eed-9234484b20f6 - STKSWI20240418061446904605 | F40: 135.5
A41: 2024-04 | B41: 04/18/2024 | C41: Journal Entry(Cash) | E41: ID: 328667d6-dc1a-441d-869b-09c3e277311b - STKSWI20240418062102904630 | F41: 30
A42: 2024-04 | B42: 04/29/2024 | C42: Journal Entry(Cash) | E42: ID: 2d1509ce-b982-474e-8b69-7d3747c17a07 - STKSWI20240429051501003566 | F42: 188.83
A43: 2024-04 | B43: 04/30/2024 | C43: Dividends | D43: QYLD | E43: Cash DIV @ 0.1723, Pos QTY: 17.541234321, Rec Date: 2024-04-23 | F43: 3.02
A44: 2024-04 | B44: 04/30/2024 | C44: Div. Adj(NRA Withheld) | D44: THW | E44: DIV tax withholding on $4.2 at 15% for tax country THA; w8w9: w8 | F44: -0.63
A45: 2024-04 | B45: 04/30/2024 | C45: Div. Adj(NRA Withheld) | D45: KLIP | E45: DIV tax withholding on $7.91 at 15% for tax country THA; w8w9: w8 | F45: -1.18
A46: 2024-04 | B46: 04/30/2024 | C46: Div. Adj(NRA Withheld) | D46: QYLD | E46: DIV tax withholding on $3.02 at 15% for tax country THA; w8w9: w8 | F46: -0.45
A47: 2024-04 | B47: 04/30/2024 | C47: Dividends | D47: KLIP | E47: Cash DIV @ 0.527163, Pos QTY: 15, Rec Date: 2024-04-29 | F47: 7.91
A48: 2024-04 | B48: 04/30/2024 | C48: Dividends | D48: THW | E48: Cash DIV @ 0.1167, Pos QTY: 36, Rec Date: 2024-04-23 | F48: 4.2
A49: 2024-05 | B49: 05/01/2024 | C49: Journal Entry(Cash) | E49: ID: 43e06528-187c-421d-bfa6-542542058edb - STKSWI20240501013431036479 | F49: 4029
A50: 2024-05 | B50: 05/03/2024 | C50: Journal Entry(Cash) | E50: ID: bce55d1a-c4c6-49ed-810a-57ffddaf5cff - STKSWO20240503123329067130 | F50: -480
A51: 2024-05 | B51: 05/07/2024 | C51: Div. Adj(NRA Withheld) | D51: SHV | E51: DIV tax withholding on $9.47 at 15% for tax country THA; w8w9: w8 | F51: -1.42
A52: 2024-05 | B52: 05/07/2024 | C52: Div. Adj(NRA Withheld) | D52: SGOV | E52: DIV tax withholding on $0.3 at 15% for tax country THA; w8w9: w8 | F52: -0.04
A53: 2024-05 | B53: 05/07/2024 | C53: Dividends | D53: SHV | E53: Cash DIV @ 0.463666, Pos QTY: 20.420107389, Rec Date: 2024-05-02 | F53: 9.47
A54: 2024-05 | B54: 05/07/2024 | C54: Dividends | D54: SGOV | E54: Cash DIV @ 0.427591, Pos QTY: 0.693025941, Rec Date: 2024-05-02 | F54: 0.3
A55: 2024-05 | B55: 05/20/2024 | C55: Journal Entry(Cash) | E55: ID: fe0c568c-b4e0-4e91-9ab2-3bcdc19b8cd7 - STKSWO20240519012557228018 | F55: -1
A56: 2024-05 | B56: 05/29/2024 | C56: Dividends | D56: RYLD | E56: Cash DIV @ 0.1654, Pos QTY: 12.825266362, Rec Date: 2024-05-21 | F56: 2.12
A57: 2024-05 | B57: 05/29/2024 | C57: Dividends | D57: QYLD | E57: Cash DIV @ 0.1628, Pos QTY: 17.541234321, Rec Date: 2024-05-21 | F57: 2.86
A58: 2024-05 | B58: 05/29/2024 | C58: Div. Adj(NRA Withheld) | D58: RYLD | E58: DIV tax withholding on $2.12 at 15% for tax country THA; w8w9: w8 | F58: -0.31
A59: 2024-05 | B59: 05/29/2024 | C59: Div. Adj(NRA Withheld) | D59: QYLD | E59: DIV tax withholding on $2.86 at 15% for tax country THA; w8w9: w8 | F59: -0.42
A60: 2024-05 | B60: 05/30/2024 | C60: Journal Entry(Cash) | E60: ID: daa674dd-0885-4691-a6d5-221fac7141a9 - STKSWI20240530051922390749 | F60: 120
A61: 2024-05 | B61: 05/31/2024 | C61: Div. Adj(NRA Withheld) | D61: KLIP | E61: DIV tax withholding on $15.24 at 15% for tax country THA; w8w9: w8 | F61: -2.28
A62: 2024-05 | B62: 05/31/2024 | C62: Dividends | D62: KLIP | E62: Cash DIV @ 0.507881, Pos QTY: 30, Rec Date: 2024-05-30 | F62: 15.24
A63: 2024-05 | B63: 05/31/2024 | C63: Div. Adj(NRA Withheld) | D63: THW | E63: DIV tax withholding on $4.55 at 15% for tax country THA; w8w9: w8 | F63: -0.68
A64: 2024-05 | B64: 05/31/2024 | C64: Dividends | D64: THW | E64: Cash DIV @ 0.1167, Pos QTY: 39, Rec Date: 2024-05-23 | F64: 4.55
A65: 2024-06 | B65: 06/03/2024 | C65: Journal Entry(Cash) | E65: ID: 432b9739-1d30-4f1a-8302-c678a16506e0 - STKSWI20240603014027449851 | F65: 1492.94
A66: 2024-06 | B66: 06/03/2024 | C66: Journal Entry(Cash) | E66: ID: 0bcc58f8-7822-40e3-b686-43fa90651a45 - STKSWI20240603022207453173 | F66: 135.9
A67: 2024-06 | B67: 06/03/2024 | C67: Journal Entry(Cash) | E67: ID: 6139b781-1ef9-4691-8e9f-a63a0074041d - STKSWI20240603025706455658 | F67: 10
A68: 2024-06 | B68: 06/06/2024 | C68: Div. Adj(NRA Withheld) | D68: FLTR | E68: DIV tax withholding on $4.97 at 15% for tax country THA; w8w9: w8 | F68: -0.74
A69: 2024-06 | B69: 06/06/2024 | C69: Dividends | D69: FLTR | E69: Cash DIV @ 0.1302, Pos QTY: 38.140942243, Rec Date: 2024-06-03 | F69: 4.97
A70: 2024-06 | B70: 06/07/2024 | C70: Div. Adj(NRA Withheld) | D70: SHV | E70: DIV tax withholding on $13.98 at 15% for tax country THA; w8w9: w8 | F70: -2.09
A71: 2024-06 | B71: 06/07/2024 | C71: Div. Adj(NRA Withheld) | D71: PFRL | E71: DIV tax withholding on $1.49 at 15% for tax country THA; w8w9: w8 | F71: -0.22
A72: 2024-06 | B72: 06/07/2024 | C72: Dividends | D72: SGOV | E72: Cash DIV @ 0.439724, Pos QTY: 11.969197426, Rec Date: 2024-06-03 | F72: 5.26
A73: 2024-06 | B73: 06/07/2024 | C73: Dividends | D73: SHV | E73: Cash DIV @ 0.472298, Pos QTY: 29.590335818, Rec Date: 2024-06-03 | F73: 13.98
A74: 2024-06 | B74: 06/07/2024 | C74: Div. Adj(NRA Withheld) | D74: SGOV | E74: DIV tax withholding on $5.26 at 15% for tax country THA; w8w9: w8 | F74: -0.78
A75: 2024-06 | B75: 06/07/2024 | C75: Div. Adj(NRA Withheld) | D75: GOOY | E75: DIV tax withholding on $4.11 at 15% for tax country THA; w8w9: w8 | F75: -0.61
A76: 2024-06 | B76: 06/07/2024 | C76: Dividends | D76: GOOY | E76: Cash DIV @ 0.6858, Pos QTY: 6, Rec Date: 2024-06-06 | F76: 4.11
A77: 2024-06 | B77: 06/07/2024 | C77: Dividends | D77: PFRL | E77: Cash DIV @ 0.3737, Pos QTY: 4, Rec Date: 2024-06-03 | F77: 1.49
A78: 2024-06 | B78: 06/17/2024 | C78: Div. Adj(NRA Withheld) | D78: MCHI | E78: DIV tax withholding on $0.34 at 15% for tax country THA; w8w9: w8 | F78: -0.05
A79: 2024-06 | B79: 06/17/2024 | C79: Dividends | D79: MCHI | E79: Cash DIV @ 0.190546, Pos QTY: 1.802738992, Rec Date: 2024-06-11 | F79: 0.34
A80: 2024-06 | B80: 06/24/2024 | C80: Journal Entry(Cash) | E80: ID: 016981e5-4d1a-4046-8611-9ba46609a0f9 - STKSWI20240624013328831826 | F80: 544.66
A81: 2024-06 | B81: 06/28/2024 | C81: Div. Adj(NRA Withheld) | D81: NDAQ | E81: DIV tax withholding on $0.25 at 15% for tax country THA; w8w9: w8 | F81: -0.03
A82: 2024-06 | B82: 06/28/2024 | C82: Div. Adj(NRA Withheld) | D82: KLIP | E82: DIV tax withholding on $23 at 15% for tax country THA; w8w9: w8 | F82: -3.45
A83: 2024-06 | B83: 06/28/2024 | C83: Dividends | D83: KLIP | E83: Cash DIV @ 0.459931, Pos QTY: 50, Rec Date: 2024-06-27 | F83: 23
A84: 2024-06 | B84: 06/28/2024 | C84: Dividends | D84: NDAQ | E84: Cash DIV @ 0.24, Pos QTY: 1.031163562, Rec Date: 2024-06-14 | F84: 0.25
A85: 2024-06 | B85: 06/28/2024 | C85: Dividends | D85: THW | E85: Cash DIV @ 0.1167, Pos QTY: 39, Rec Date: 2024-06-21 | F85: 4.55
A86: 2024-06 | B86: 06/28/2024 | C86: Div. Adj(NRA Withheld) | D86: THW | E86: DIV tax withholding on $4.55 at 15% for tax country THA; w8w9: w8 | F86: -0.68
A87: 2024-07 | B87: 07/01/2024 | C87: Journal Entry(Cash) | E87: ID: 7970ca21-8ea9-4011-a68d-9a65c190219d - STKSWI20240701021550010994 | F87: 1899.07
A88: 2024-07 | B88: 07/01/2024 | C88: Dividends | D88: QYLD | E88: Cash DIV @ 0.1686, Pos QTY: 17.541234321, Rec Date: 2024-06-24 | F88: 2.96
A89: 2024-07 | B89: 07/01/2024 | C89: Div. Adj(NRA Withheld) | D89: RYLD | E89: DIV tax withholding on $2.28 at 15% for tax country THA; w8w9: w8 | F89: -0.34
A90: 2024-07 | B90: 07/01/2024 | C90: Div. Adj(NRA Withheld) | D90: QYLD | E90: DIV tax withholding on $2.96 at 15% for tax country THA; w8w9: w8 | F90: -0.44
A91: 2024-07 | B91: 07/01/2024 | C91: Dividends | D91: RYLD | E91: Cash DIV @ 0.1608, Pos QTY: 14.175986007, Rec Date: 2024-06-24 | F91: 2.28
A92: 2024-07 | B92: 07/05/2024 | C92: Dividends | D92: VNAM | E92: Cash DIV @ 0.002333, Pos QTY: 4, Rec Date: 2024-06-27 | F92: 0.01
A93: 2024-07 | B93: 07/05/2024 | C93: Dividends | D93: SHV | E93: Cash DIV @ 0.466218, Pos QTY: 35.523463203, Rec Date: 2024-07-01 | F93: 16.56
A94: 2024-07 | B94: 07/05/2024 | C94: Div. Adj(NRA Withheld) | D94: FLTR | E94: DIV tax withholding on $6 at 15% for tax country THA; w8w9: w8 | F94: -0.9
A95: 2024-07 | B95: 07/05/2024 | C95: Div. Adj(NRA Withheld) | D95: SHV | E95: DIV tax withholding on $16.56 at 15% for tax country THA; w8w9: w8 | F95: -2.48
A96: 2024-07 | B96: 07/05/2024 | C96: Dividends | D96: SGOV | E96: Cash DIV @ 0.4388, Pos QTY: 16.524166029, Rec Date: 2024-07-01 | F96: 7.25
A97: 2024-07 | B97: 07/05/2024 | C97: Div. Adj(NRA Withheld) | D97: SGOV | E97: DIV tax withholding on $7.25 at 15% for tax country THA; w8w9: w8 | F97: -1.08
A98: 2024-07 | B98: 07/05/2024 | C98: Dividends | D98: FLTR | E98: Cash DIV @ 0.1284, Pos QTY: 46.723644332, Rec Date: 2024-07-01 | F98: 6
A99: 2024-07 | B99: 07/08/2024 | C99: Dividends | D99: PFRL | E99: Cash DIV @ 0.33133, Pos QTY: 6, Rec Date: 2024-07-01 | F99: 1.99
... A106: 2024-07 | B106: 07/08/2024 | C106: Div. Adj(NRA Withheld) | D106: CONY | E106: DIV tax withholding on $28.32 at 15% for tax country THA; w8w9: w8 | F106: -4.24
...

Sheet Fees
A1: Month | B1: Trade Date | C1: Description | D1: Net Amt
A2: 2025-02 | B2: 02/10/2025 | C2: REG fee for proceed of $445.55 on 2025-02-10 by 947159514 | D2: -0.02
A3: 2025-02 | B3: 02/10/2025 | C3: TAF fee for proceed of 9.02418951 shares (2 trades) on 2025-02-10 by 947159514 | D3: -0.01
A4: 2025-04 | B4: 04/07/2025 | C4: REG fee for proceed of $84.66 on 2025-04-07 by 947159514 | D4: -0.01
A5: 2025-04 | B5: 04/07/2025 | C5: TAF fee for proceed of 1.802738992 shares (2 trades) on 2025-04-07 by 947159514 | D5: -0.01
A6: 2025-04 | B6: 04/21/2025 | C6: REG fee for proceed of $878.6 on 2025-04-21 by 947159514 | D6: -0.03
A7: 2025-04 | B7: 04/21/2025 | C7: TAF fee for proceed of 58.138237982 shares (2 trades) on 2025-04-21 by 947159514 | D7: -0.01
A8: 2025-05 | B8: 05/16/2025 | C8: TAF fee for proceed of 55 shares (1 trades) on 2025-05-16 by 947159514 | D8: -0.01
A9: 2025-06 | B9: 06/10/2025 | C9: CAT fee for proceed of 1 trades on 2025-06-10 by 947159514 | D9: -0.01
A10: 2025-06 | B10: 06/11/2025 | C10: CAT fee for proceed of 1 trades on 2025-06-11 by 947159514 | D10: -0.01
A11: 2025-06 | B11: 06/12/2025 | C11: CAT fee for proceed of 1 trades on 2025-06-12 by 947159514 | D11: -0.01
A12: 2025-06 | B12: 06/13/2025 | C12: CAT fee for proceed of 9 trades on 2025-06-13 by 947159514 | D12: -0.01
A13: 2025-06 | B13: 06/13/2025 | C13: TAF fee for proceed of 31 shares (2 trades) on 2025-06-13 by 947159514 | D13: -0.01
... A75: 2026-04 | B75: 04/28/2026 | C75: TAF fee for proceed of 13.649461997 shares (2 trades) on 2026-04-28 by 947159514 | D75: -0.01

Sheet Deposits & Withdrawals
A1: Month | B1: Trade Date | C1: Entry Type | D1: Description | E1: Net Amt | F1: Account No
A2: 2024-11 | B2: 11/01/2024 | C2: Journal Entry(Cash) | D2: STKSWI20241101032526417426 | E2: 881.05 | F2: 947159514
A3: 2024-11 | B3: 11/01/2024 | C3: Journal Entry(Cash) | D3: STKSWI20241101033632417975 | E3: 587.37 | F3: 947159514
A4: 2024-11 | B4: 11/25/2024 | C4: Journal Entry(Cash) | D4: STKSWI20241125042536876644 | E4: 287.52 | F4: 947159514
A5: 2024-11 | B5: 11/27/2024 | C5: Journal Entry(Cash) | D5: STKSWI20241127044827937623 | E5: 1445.92 | F5: 947159514
A6: 2024-12 | B6: 12/20/2024 | C6: Journal Entry(Cash) | D6: STKSWI20241220034703511182 | E6: 193.76 | F6: 947159514
A7: 2024-12 | B7: 12/20/2024 | C7: Journal Entry(Cash) | D7: STKSWI20241220035008511413 | E7: 184 | F7: 947159514
A8: 2024-12 | B8: 12/23/2024 | C8: Journal Entry(Cash) | D8: STKSWI20241223033928553487 | E8: 184 | F8: 947159514
A9: 2024-12 | B9: 12/23/2024 | C9: Journal Entry(Cash) | D9: STKSWI20241223034107553610 | E9: 184 | F9: 947159514
A10: 2024-12 | B10: 12/31/2024 | C10: Journal Entry(Cash) | D10: STKSWI20241231053543777802 | E10: 183 | F10: 947159514
A11: 2024-12 | B11: 12/31/2024 | C11: Journal Entry(Cash) | D11: STKSWI20241231044607776220 | E11: 367 | F11: 947159514
A12: 2024-12 | B12: 12/31/2024 | C12: Journal Entry(Cash) | D12: STKSWI20241231052307777157 | E12: 183 | F12: 947159514
A13: 2024-12 | B13: 12/31/2024 | C13: Journal Entry(Cash) | D13: STKSWI20241231052614777300 | E13: 173.64 | F13: 947159514
... A202: 2026-04 | B202: 04/13/2026 | C202: Journal Entry(Cash) | D202: STKSWI20260413021419162696 | E202: 156 | F202: 947159514

Sheet Validation
A1: Month | B1: Cash Identity Diff ($) | C1: Txn Sum vs Trade Transaction ($) | D1: Gross Dividends Sum vs Summary ($) | E1: Holdings Sum vs Long ($) | F1: Prior Ending vs Beginning ($) | G1: Note
A2: 2023-01 | B2: =ROUND(Summary!D2+Summary!E2-Summary!F2+Summary!G2+Summary!H2-Summary!I2,2) -> 0 | C2: =ROUND(SUMIFS(Transactions!I:I,Transactions!A:A,A2)-Summary!G2,2) -> 0 | D2: =ROUND(SUMIFS(Income!F:F,Income!A:A,A2,Income!C:C,"Dividends")-Summary!L2,2) -> 0 | E2: =ROUND(SUMIFS(Holdings!F:F,Holdings!A:A,A2,Holdings!B:B,"<>*Cash")-Summary!J2,2) -> 0 | G2: Holdings diff of few cents = statement's own per-row rounding (verified against PDF text)
A3: 2023-02 | B3: =ROUND(Summary!D3+Summary!E3-Summary!F3+Summary!G3+Summary!H3-Summary!I3,2) -> 0 | C3: =ROUND(SUMIFS(Transactions!I:I,Transactions!A:A,A3)-Summary!G3,2) -> 0 | D3: =ROUND(SUMIFS(Income!F:F,Income!A:A,A3,Income!C:C,"Dividends")-Summary!L3,2) -> 0 | E3: =ROUND(SUMIFS(Holdings!F:F,Holdings!A:A,A3,Holdings!B:B,"<>*Cash")-Summary!J3,2) -> 0 | F3: =ROUND(Summary!I2-Summary!D3,2) -> 0 | G3: Holdings diff of few cents = statement's own per-row rounding (verified against PDF text)
A4: 2023-03 | B4: =ROUND(Summary!D4+Summary!E4-Summary!F4+Summary!G4+Summary!H4-Summary!I4,2) -> 0 | C4: =ROUND(SUMIFS(Transactions!I:I,Transactions!A:A,A4)-Summary!G4,2) -> 0 | D4: =ROUND(SUMIFS(Income!F:F,Income!A:A,A4,Income!C:C,"Dividends")-Summary!L4,2) -> 0 | E4: =ROUND(SUMIFS(Holdings!F:F,Holdings!A:A,A4,Holdings!B:B,"<>*Cash")-Summary!J4,2) -> 0 | F4: =ROUND(Summary!I3-Summary!D4,2) -> 0 | G4: Holdings diff of few cents = statement's own per-row rounding (verified against PDF text)
A5: 2023-04 | B5: =ROUND(Summary!D5+Summary!E5-Summary!F5+Summary!G5+Summary!H5-Summary!I5,2) -> 0 | C5: =ROUND(SUMIFS(Transactions!I:I,Transactions!A:A,A5)-Summary!G5,2) -> 0 | D5: =ROUND(SUMIFS(Income!F:F,Income!A:A,A5,Income!C:C,"Dividends")-Summary!L5,2) -> 0 | E5: =ROUND(SUMIFS(Holdings!F:F,Holdings!A:A,A5,Holdings!B:B,"<>*Cash")-Summary!J5,2) -> 0 | F5: =ROUND(Summary!I4-Summary!D5,2) -> 0 | G5: Holdings diff of few cents = statement's own per-row rounding (verified against PDF text)
A6: 2023-05 | B6: =ROUND(Summary!D6+Summary!E6-Summary!F6+Summary!G6+Summary!H6-Summary!I6,2) -> 0 | C6: =ROUND(SUMIFS(Transactions!I:I,Transactions!A:A,A6)-Summary!G6,2) -> 0 | D6: =ROUND(SUMIFS(Income!F:F,Income!A:A,A6,Income!C:C,"Dividends")-Summary!L6,2) -> 0 | E6: =ROUND(SUMIFS(Holdings!F:F,Holdings!A:A,A6,Holdings!B:B,"<>*Cash")-Summary!J6,2) -> 0 | F6: =ROUND(Summary!I5-Summary!D6,2) -> 0 | G6: Holdings diff of few cents = statement's own per-row rounding (verified against PDF text)
A7: 2023-06 | B7: =ROUND(Summary!D7+Summary!E7-Summary!F7+Summary!G7+Summary!H7-Summary!I7,2) -> 0 | C7: =ROUND(SUMIFS(Transactions!I:I,Transactions!A:A,A7)-Summary!G7,2) -> 0 | D7: =ROUND(SUMIFS(Income!F:F,Income!A:A,A7,Income!C:C,"Dividends")-Summary!L7,2) -> 0 | E7: =ROUND(SUMIFS(Holdings!F:F,Holdings!A:A,A7,Holdings!B:B,"<>*Cash")-Summary!J7,2) -> 0 | F7: =ROUND(Summary!I6-Summary!D7,2) -> 0 | G7: Holdings diff of few cents = statement's own per-row rounding (verified against PDF text)
A8: 2023-07 | B8: =ROUND(Summary!D8+Summary!E8-Summary!F8+Summary!G8+Summary!H8-Summary!I8,2) -> 0 | C8: =ROUND(SUMIFS(Transactions!I:I,Transactions!A:A,A8)-Summary!G8,2) -> 0 | D8: =ROUND(SUMIFS(Income!F:F,Income!A:A,A8,Income!C:C,"Dividends")-Summary!L8,2) -> 0 | E8: =ROUND(SUMIFS(Holdings!F:F,Holdings!A:A,A8,Holdings!B:B,"<>*Cash")-Summary!J8,2) -> -0.01 | F8: =ROUND(Summary!I7-Summary!D8,2) -> 0 | G8: Holdings diff of few cents = statement's own per-row rounding (verified against PDF text)
A9: 2023-08 | B9: =ROUND(Summary!D9+Summary!E9-Summary!F9+Summary!G9+Summary!H9-Summary!I9,2) -> 0 | C9: =ROUND(SUMIFS(Transactions!I:I,Transactions!A:A,A9)-Summary!G9,2) -> 0 | D9: =ROUND(SUMIFS(Income!F:F,Income!A:A,A9,Income!C:C,"Dividends")-Summary!L9,2) -> 0 | E9: =ROUND(SUMIFS(Holdings!F:F,Holdings!A:A,A9,Holdings!B:B,"<>*Cash")-Summary!J9,2) -> 0.01 | F9: =ROUND(Summary!I8-Summary!D9,2) -> 0 | G9: Holdings diff of few cents = statement's own per-row rounding (verified against PDF text)
A10: 2023-09 | B10: =ROUND(Summary!D10+Summary!E10-Summary!F10+Summary!G10+Summary!H10-Summary!I10,2) -> 0 | C10: =ROUND(SUMIFS(Transactions!I:I,Transactions!A:A,A10)-Summary!G10,2) -> 0 | D10: =ROUND(SUMIFS(Income!F:F,Income!A:A,A10,Income!C:C,"Dividends")-Summary!L10,2) -> 0 | E10: =ROUND(SUMIFS(Holdings!F:F,Holdings!A:A,A10,Holdings!B:B,"<>*Cash")-Summary!J10,2) -> 0 | F10: =ROUND(Summary!I9-Summary!D10,2) -> 0 | G10: Holdings diff of few cents = statement's own per-row rounding (verified against PDF text)
A11: 2023-10 | B11: =ROUND(Summary!D11+Summary!E11-Summary!F11+Summary!G11+Summary!H11-Summary!I11,2) -> 0 | C11: =ROUND(SUMIFS(Transactions!I:I,Transactions!A:A,A11)-Summary!G11,2) -> 0 | D11: =ROUND(SUMIFS(Income!F:F,Income!A:A,A11,Income!C:C,"Dividends")-Summary!L11,2) -> 0 | E11: =ROUND(SUMIFS(Holdings!F:F,Holdings!A:A,A11,Holdings!B:B,"<>*Cash")-Summary!J11,2) -> 0.01 | F11: =ROUND(Summary!I10-Summary!D11,2) -> 0 | G11: Holdings diff of few cents = statement's own per-row rounding (verified against PDF text)
A12: 2023-11 | B12: =ROUND(Summary!D12+Summary!E12-Summary!F12+Summary!G12+Summary!H12-Summary!I12,2) -> 0 | C12: =ROUND(SUMIFS(Transactions!I:I,Transactions!A:A,A12)-Summary!G12,2) -> 0 | D12: =ROUND(SUMIFS(Income!F:F,Income!A:A,A12,Income!C:C,"Dividends")-Summary!L12,2) -> 0 | E12: =ROUND(SUMIFS(Holdings!F:F,Holdings!A:A,A12,Holdings!B:B,"<>*Cash")-Summary!J12,2) -> 0 | F12: =ROUND(Summary!I11-Summary!D12,2) -> 0 | G12: Holdings diff of few cents = statement's own per-row rounding (verified against PDF text)
A13: 2023-12 | B13: =ROUND(Summary!D13+Summary!E13-Summary!F13+Summary!G13+Summary!H13-Summary!I13,2) -> 0 | C13: =ROUND(SUMIFS(Transactions!I:I,Transactions!A:A,A13)-Summary!G13,2) -> 0 | D13: =ROUND(SUMIFS(Income!F:F,Income!A:A,A13,Income!C:C,"Dividends")-Summary!L13,2) -> 0 | E13: =ROUND(SUMIFS(Holdings!F:F,Holdings!A:A,A13,Holdings!B:B,"<>*Cash")-Summary!J13,2) -> 0 | F13: =ROUND(Summary!I12-Summary!D13,2) -> 0 | G13: Holdings diff of few cents = statement's own per-row rounding (verified against PDF text)
A14: 2024-01 | B14: =ROUND(Summary!D14+Summary!E14-Summary!F14+Summary!G14+Summary!H14-Summary!I14,2) -> 0 | C14: =ROUND(SUMIFS(Transactions!I:I,Transactions!A:A,A14)-Summary!G14,2) -> 0 | D14: =ROUND(SUMIFS(Income!F:F,Income!A:A,A14,Income!C:C,"Dividends")-Summary!L14,2) -> 0 | E14: =ROUND(SUMIFS(Holdings!F:F,Holdings!A:A,A14,Holdings!B:B,"<>*Cash")-Summary!J14,2) -> 0 | F14: =ROUND(Summary!I13-Summary!D14,2) -> 0 | G14: Holdings diff of few cents = statement's own per-row rounding (verified against PDF text)
... A41: 2026-04 | B41: =ROUND(Summary!D41+Summary!E41-Summary!F41+Summary!G41+Summary!H41-Summary!I41,2) -> 0 | C41: =ROUND(SUMIFS(Transactions!I:I,Transactions!A:A,A41)-Summary!G41,2) -> 0 | D41: =ROUND(SUMIFS(Income!F:F,Income!A:A,A41,Income!C:C,"Dividends")-Summary!L41,2) -> 0 | E41: =ROUND(SUMIFS(Holdings!F:F,Holdings!A:A,A41,Holdings!B:B,"<>*Cash")-Summary!J41,2) -> 0.02 | F41: =ROUND(Summary!I40-Summary!D41,2) -> 0 | G41: Holdings diff of few cents = statement's own per-row rounding (verified against PDF text)
